{
  "msg": "success",
  "code": 0,
  "data": {
    "records": [
      {
        "id": 80513,
        "newsTitle": "想放弃的时候，就去逛一逛菜市场吧",
        "newsBriefly": "到菜市场去，当代人的心灵大保健",
        "titleImg": null,
        "rssName": "有间大学",
        "time": "2021-06-04T12:04:42.000+0000",
        "sourceUrl": "http://mp.weixin.qq.com/s?__biz=MzU2MDAzNzY1Mg==&mid=2247520920&idx=2&sn=9214fa2d2e4248fee5ff8ecde5a066d2&chksm=fc0cf8e3cb7b71f5ab72d2be8a6da62a32d36e5d8a4325a56213ec3989298fccb50841cbe39d",
        "soureId": 163,
        "isSubscribe": null
      },
      {
        "id": 80514,
        "newsTitle": "李安最好看的电影，都已经拍完了？",
        "newsBriefly": "李安并没有错，他只是比时代超前了一步。",
        "titleImg": null,
        "rssName": "有间大学",
        "time": "2021-06-04T12:04:42.000+0000",
        "sourceUrl": "http://mp.weixin.qq.com/s?__biz=MzU2MDAzNzY1Mg==&mid=2247520920&idx=1&sn=630ffb34fce82cfa888cd7dbef6e3573&chksm=fc0cf8e3cb7b71f5521d6ce0919d14a5c9fb9b36166b65578f2687e9c10a5128128e05fba1e9",
        "soureId": 163,
        "isSubscribe": null
      },
      {
        "id": 80515,
        "newsTitle": "《暮光之城》，一部让男主角疯狂吐槽的玛丽苏电影",
        "newsBriefly": "狗血又玛丽苏的《暮光之城》，当年凭什么火遍全球？",
        "titleImg": null,
        "rssName": "有间大学",
        "time": "2021-06-03T10:33:27.000+0000",
        "sourceUrl": "http://mp.weixin.qq.com/s?__biz=MzU2MDAzNzY1Mg==&mid=2247520710&idx=2&sn=bd93ababc27d6c84a56f3b3780733078&chksm=fc0cfbbdcb7b72ab751a743c0731287c1901d64ed1acd6537f3b60638b48bc1b5044fff18d1d",
        "soureId": 163,
        "isSubscribe": null
      },
      {
        "id": 80516,
        "newsTitle": "最难脱单的工作，它排第一",
        "newsBriefly": "职场爱情从来不易，也没有捷径。",
        "titleImg": null,
        "rssName": "有间大学",
        "time": "2021-06-03T10:33:27.000+0000",
        "sourceUrl": "http://mp.weixin.qq.com/s?__biz=MzU2MDAzNzY1Mg==&mid=2247520710&idx=1&sn=4fb8c71455a76b41e66106bc02d6e0bf&chksm=fc0cfbbdcb7b72ab72f147278323063c9cf825817b764e0494b3fb0bf2f0b83bccd1096385fd",
        "soureId": 163,
        "isSubscribe": null
      },
      {
        "id": 80517,
        "newsTitle": "这个最冷门专业，解决了中国人的吃饭问题",
        "newsBriefly": "它走红的时候，你还没出生。",
        "titleImg": null,
        "rssName": "有间大学",
        "time": "2021-06-02T10:31:21.000+0000",
        "sourceUrl": "http://mp.weixin.qq.com/s?__biz=MzU2MDAzNzY1Mg==&mid=2247520660&idx=1&sn=0e1446551a05d5707377bab314eeda6c&chksm=fc0cfbefcb7b72f9a5ea559dce88514888814aafe5b76248b464758dfd5f5d59bd7c19c06194",
        "soureId": 163,
        "isSubscribe": null
      },
      {
        "id": 80518,
        "newsTitle": "好评率超高的8个公众号，你关注了吗",
        "newsBriefly": "荐号",
        "titleImg": null,
        "rssName": "有间大学",
        "time": "2021-06-01T11:12:17.000+0000",
        "sourceUrl": "http://mp.weixin.qq.com/s?__biz=MzU2MDAzNzY1Mg==&mid=2247520652&idx=2&sn=155d166e97d8f98be303fb01f4fe71f7&chksm=fc0cfbf7cb7b72e1bb3ffcb8c4f1bc5e2b6bd42601647709b78b1b8416b4ddabe82a587aa979",
        "soureId": 163,
        "isSubscribe": null
      },
      {
        "id": 80519,
        "newsTitle": "窥探名校生活，比在线吃瓜还过瘾",
        "newsBriefly": "“名校Vlog”，让我又爱又恨。",
        "titleImg": null,
        "rssName": "有间大学",
        "time": "2021-06-01T11:12:17.000+0000",
        "sourceUrl": "http://mp.weixin.qq.com/s?__biz=MzU2MDAzNzY1Mg==&mid=2247520652&idx=1&sn=30ba3ba549fc2b41478a74a3df587ff3&chksm=fc0cfbf7cb7b72e198e60d69fc30d4576b9e651bf6eb73087892a6dbef514d29c0f23034c78a",
        "soureId": 163,
        "isSubscribe": null
      },
      {
        "id": 80520,
        "newsTitle": "女生吸脂的焦虑，男人根本不懂",
        "newsBriefly": "改变生活的，到底是漫长的观念变化，还是一场快速的医美手术？",
        "titleImg": null,
        "rssName": "有间大学",
        "time": "2021-05-31T10:07:23.000+0000",
        "sourceUrl": "http://mp.weixin.qq.com/s?__biz=MzU2MDAzNzY1Mg==&mid=2247520635&idx=1&sn=b59fb6f1e5111fa5f2c89c0efde211fc&chksm=fc0cfb00cb7b72165cd718f22592eba540eaefdb315270d7f9d16e0fb6b29a55fb26a654fbee",
        "soureId": 163,
        "isSubscribe": null
      },
      {
        "id": 80521,
        "newsTitle": "一个人读了硕博士的改变",
        "newsBriefly": "推荐",
        "titleImg": null,
        "rssName": "有间大学",
        "time": "2021-05-28T10:10:18.000+0000",
        "sourceUrl": "http://mp.weixin.qq.com/s?__biz=MzU2MDAzNzY1Mg==&mid=2247520504&idx=2&sn=105441511b2160cdeb8c89ae03894d9e&chksm=fc0cfa83cb7b739533e727d266f6a9ef5ee3a6f1a922452c7216b9725f9d60281c2e89605376",
        "soureId": 163,
        "isSubscribe": null
      },
      {
        "id": 80522,
        "newsTitle": "中国女孩最渴望的精致，普通人学不来",
        "newsBriefly": "真实的生活不可能每时每刻都在拍摄Vlog。",
        "titleImg": null,
        "rssName": "有间大学",
        "time": "2021-05-28T10:10:18.000+0000",
        "sourceUrl": "http://mp.weixin.qq.com/s?__biz=MzU2MDAzNzY1Mg==&mid=2247520504&idx=1&sn=bb71d7c5aa87088f45eb97ef85ffd3ae&chksm=fc0cfa83cb7b73958ff833203e7593395d2de87f1a066d48a53f0dbf689034b1a837766b6809",
        "soureId": 163,
        "isSubscribe": null
      },
      {
        "id": 8496,
        "newsTitle": "150多年了，我们还没有读懂进化论",
        "newsBriefly": "“进化论”这个词儿，就是我们对进化论最大的误解。",
        "titleImg": null,
        "rssName": "有间大学",
        "time": "2021-05-21T11:25:51.000+0000",
        "sourceUrl": "http://mp.weixin.qq.com/s?__biz=MzU2MDAzNzY1Mg==&mid=2247519182&idx=2&sn=60433f21bb81ebf3438f1ea734f4e5e5&chksm=fc0ce1b5cb7b68a351f02e55a82ee1714e9378fde16427caed1f93247f70cec6429347744008",
        "soureId": 163,
        "isSubscribe": null
      },
      {
        "id": 8497,
        "newsTitle": "这些小学生美妆博主的手法，yyds？",
        "newsBriefly": "“别看了，小学生化眼线比你还稳。”",
        "titleImg": null,
        "rssName": "有间大学",
        "time": "2021-05-21T11:25:51.000+0000",
        "sourceUrl": "http://mp.weixin.qq.com/s?__biz=MzU2MDAzNzY1Mg==&mid=2247519182&idx=1&sn=cc1bf0888be243cd4554af1d458453cd&chksm=fc0ce1b5cb7b68a3456d16b43cd9fb3a5b9b7ff7384c3f5ed5186c96d95ca6c19bd1abb98ad9",
        "soureId": 163,
        "isSubscribe": null
      },
      {
        "id": 8498,
        "newsTitle": "求求这些化妆品牌，不要再给口红起奇怪的名字了",
        "newsBriefly": "现在的化妆品牌，起名字越来越矫情了。",
        "titleImg": null,
        "rssName": "有间大学",
        "time": "2021-05-20T09:45:08.000+0000",
        "sourceUrl": "http://mp.weixin.qq.com/s?__biz=MzU2MDAzNzY1Mg==&mid=2247518925&idx=2&sn=c70b2852d575ce4399a979e3f07491f0&chksm=fc0ce0b6cb7b69a0a94e6b54530ebbf29960d5f1823a7920511facd112d63b59be34ebc5c5e2",
        "soureId": 163,
        "isSubscribe": null
      },
      {
        "id": 8499,
        "newsTitle": "谁都没资格说，他们不是读书的料",
        "newsBriefly": "在苦读背后，农家子弟有怎么样的世界？",
        "titleImg": null,
        "rssName": "有间大学",
        "time": "2021-05-20T09:45:08.000+0000",
        "sourceUrl": "http://mp.weixin.qq.com/s?__biz=MzU2MDAzNzY1Mg==&mid=2247518925&idx=1&sn=32edd88dea61825fcef61f27a5fdc3e2&chksm=fc0ce0b6cb7b69a00b4ce571e923236f20cad820b96999f4c4df8ff99faf389d850ff84a8f3c",
        "soureId": 163,
        "isSubscribe": null
      },
      {
        "id": 8500,
        "newsTitle": "单凭富豪校友，拯救不了大学的捐款",
        "newsBriefly": "谁又捐了过亿元？",
        "titleImg": null,
        "rssName": "有间大学",
        "time": "2021-05-19T12:00:54.000+0000",
        "sourceUrl": "http://mp.weixin.qq.com/s?__biz=MzU2MDAzNzY1Mg==&mid=2247518871&idx=2&sn=21161063b052121f8b02173fa7cdccb7&chksm=fc0ce0eccb7b69fae106e9fbfcedd86bd5af1a3db86fd1a34e247b0a989d7ae5bddaf8732908",
        "soureId": 163,
        "isSubscribe": null
      },
      {
        "id": 8501,
        "newsTitle": "最敢反内卷的，可能是这些97后",
        "newsBriefly": "97后的世界，有什么不一样？",
        "titleImg": null,
        "rssName": "有间大学",
        "time": "2021-05-19T12:00:54.000+0000",
        "sourceUrl": "http://mp.weixin.qq.com/s?__biz=MzU2MDAzNzY1Mg==&mid=2247518871&idx=1&sn=7f368c1a964c0f84f8f95a25430a0f3a&chksm=fc0ce0eccb7b69fae8ae6bdfb154ad6e851eed603144c14a23e5e50a9bb17ac567167e6ab86e",
        "soureId": 163,
        "isSubscribe": null
      },
      {
        "id": 8502,
        "newsTitle": "如何花费少量时间更能快速提升自己？",
        "newsBriefly": "推荐",
        "titleImg": null,
        "rssName": "有间大学",
        "time": "2021-05-18T11:43:13.000+0000",
        "sourceUrl": "http://mp.weixin.qq.com/s?__biz=MzU2MDAzNzY1Mg==&mid=2247518763&idx=2&sn=0a674fe5509b181eb7452a401418f4aa&chksm=fc0ce050cb7b694622b93d3117372d2ac59bd09662d3ab5d59b53f906c325f0f7a87169ba0da",
        "soureId": 163,
        "isSubscribe": null
      },
      {
        "id": 8503,
        "newsTitle": "“清北生扎堆教培工厂，我还有机会吗？”",
        "newsBriefly": "选拔制度下的优胜者，最终又回到了系统。",
        "titleImg": null,
        "rssName": "有间大学",
        "time": "2021-05-18T11:43:13.000+0000",
        "sourceUrl": "http://mp.weixin.qq.com/s?__biz=MzU2MDAzNzY1Mg==&mid=2247518763&idx=1&sn=ee4ae6c41c6aa9cf917de0dca43620b0&chksm=fc0ce050cb7b6946aded15c53071d0b1e92b06d08e0583cab30f0e045be29535611682cce4be",
        "soureId": 163,
        "isSubscribe": null
      },
      {
        "id": 8504,
        "newsTitle": "今天的年轻人只想着实现“小目标”，不追问意义",
        "newsBriefly": "中国传统文化对于当今年轻人有何意义？",
        "titleImg": null,
        "rssName": "有间大学",
        "time": "2021-05-17T10:22:19.000+0000",
        "sourceUrl": "http://mp.weixin.qq.com/s?__biz=MzU2MDAzNzY1Mg==&mid=2247518702&idx=2&sn=1f38a21788e0277bcc6d0ba7818fe4bc&chksm=fc0ce395cb7b6a838a73e90c2ce2c0caab1a374a53f0dd15a8a921dfc808fa3fcc9d6199c026",
        "soureId": 163,
        "isSubscribe": null
      },
      {
        "id": 8505,
        "newsTitle": "所谓爱情，就是一场终生难以痊愈的大病",
        "newsBriefly": "要过多少次情人节，才能读懂恋人的心？",
        "titleImg": null,
        "rssName": "有间大学",
        "time": "2021-05-17T10:22:19.000+0000",
        "sourceUrl": "http://mp.weixin.qq.com/s?__biz=MzU2MDAzNzY1Mg==&mid=2247518702&idx=1&sn=a2e3e6ea5270becb6376b7cb27d0f95f&chksm=fc0ce395cb7b6a8334a544f6ecbd80c613bb0738b9c97540863f4d2f57a9fe4d8b5f54a3ba73",
        "soureId": 163,
        "isSubscribe": null
      }
    ],
    "total": 30,
    "size": 20,
    "current": 1,
    "background": ""
  }
}
